inlineedit/__init__.py
inlineedit/access.py
inlineedit/apps.py
inlineedit/urls.py
inlineedit/views.py
inlineedit/adaptors/__init__.py
inlineedit/adaptors/basic.py
inlineedit/adaptors/ckeditor.py
inlineedit/adaptors/markdown.py
inlineedit/adaptors/selector.py
inlineedit/migrations/__init__.py
inlineedit/migrations/__pycache__/__init__.cpython-37.pyc
inlineedit/templates/inlineedit/default.html
inlineedit/templates/inlineedit/default_bevahiour.html
inlineedit/templates/inlineedit/extendable.html
inlineedit/templates/inlineedit/fixed.html
inlineedit/templatetags/__init__.py
inlineedit/templatetags/inlineedit.py
inlineedit/templatetags/inlineedit_default_script.py
inlineedit/templatetags/__pycache__/__init__.cpython-36.pyc
inlineedit/templatetags/__pycache__/__init__.cpython-37.pyc
inlineedit/templatetags/__pycache__/activity_tags.cpython-36.pyc
inlineedit/templatetags/__pycache__/activity_tags.cpython-37.pyc
inlineedit/templatetags/__pycache__/inlineedit.cpython-37.pyc
inlineedit/templatetags/__pycache__/inlineedit_default_script.cpython-37.pyc
django_inlineedit-1.2.dist-info/LICENSE
django_inlineedit-1.2.dist-info/METADATA
django_inlineedit-1.2.dist-info/WHEEL
django_inlineedit-1.2.dist-info/top_level.txt
django_inlineedit-1.2.dist-info/RECORD
