Metadata-Version: 2.1
Name: django-inlineedit
Version: 1.2
Summary: Add inline editble fields to your templates
Home-page: https://github.com/ptav/django-inlineedit
Author: Pedro Tavares
Author-email: web@ptavares.com
License: LICENSE
Keywords: django,forms,editing
Platform: UNKNOWN
Classifier: Programming Language :: Python
Classifier: Topic :: Software Development :: Libraries :: Python Modules
Classifier: Framework :: Django
Classifier: Environment :: Web Environment
Classifier: Development Status :: 4 - Beta
Classifier: Programming Language :: Python
Classifier: Programming Language :: Python :: 3.6
Requires-Dist: django
